tests/__init__.py
tests/test.py
tystream/__init__.py
tystream/cache_handler.py
tystream/exceptions.py
tystream/logger.py
tystream/async_api/__init__.py
tystream/async_api/base.py
tystream/async_api/oauth.py
tystream/async_api/twitch.py
tystream/async_api/youtube.py
tystream/models/__init__.py
tystream/models/twitch.py
tystream/models/youtube.py
tystream/sync_api/__init__.py
tystream/sync_api/base.py
tystream/sync_api/oauth.py
tystream/sync_api/twitch.py
tystream/sync_api/youtube.py
tystream-1.6.1.1.dist-info/LICENSE.md
tystream-1.6.1.1.dist-info/METADATA
tystream-1.6.1.1.dist-info/WHEEL
tystream-1.6.1.1.dist-info/top_level.txt
tystream-1.6.1.1.dist-info/RECORD
