Metadata-Version: 2.2
Name: tystream
Version: 1.6.1.1
Summary: A Python library for Twitch & Youtube Stream Notification.
Home-page: https://github.com/Mantouisyummy/TYStream
Author: Mantouisyummy
Author-email: opcantel@gmail.com
License: GNU
Project-URL: Issue Tracker, https://github.com/Mantouisyummy/TYStream
Keywords: Twitch,Youtube,stream,stream Notification,Notification
Classifier: Programming Language :: Python :: 3.10
Classifier: Programming Language :: Python :: 3.11
Classifier: Programming Language :: Python :: 3.12
Classifier: License :: OSI Approved :: GNU General Public License v3 (GPLv3)
Classifier: Operating System :: OS Independent
Classifier: Natural Language :: English
Requires-Python: >=3.10
License-File: LICENSE.md
Requires-Dist: requests>=2.32.3
Requires-Dist: colorlog>=6.9.0
Requires-Dist: aiohttp>=3.11.13
Requires-Dist: yt-dlp>=2025.2.19
Requires-Dist: pydantic>=2.10.6
Dynamic: author
Dynamic: author-email
Dynamic: classifier
Dynamic: description
Dynamic: description-content-type
Dynamic: home-page
Dynamic: keywords
Dynamic: license
Dynamic: project-url
Dynamic: requires-dist
Dynamic: requires-python
Dynamic: summary
